[
  {
    "title": "阿勒颇的早晨",
    "text": [
      "阳光穿过灰色的云", 
      "尽头是面苍白的墙",
      "",
      "在一处阴暗的角落",
      "有只受伤的鸽子在呻吟",
      "",
      "房子默默地抽着烟",
      "一边跟人讲诉昨夜的故事",
      "",
      "橄榄树即使裂开了",
      "依旧费力地结出果子",
      "",
      "木门小声地拉开",
      "漏出了一个绿色的影子",
      "",
      "2016.10.31"
    ],
    "created_at": "2016-10-31"
  },
  {
    "title": "无题",
    "text": [
      "街道上", 
      "叫卖声汽车声谈话声风声",
      "声",
      "  声",
      "    声",
      "      声",
      "——杂乱的黑线团！",
      "",
      "2015.3.22"
    ],
    "created_at": "2015-03-22"
  },
  {
    "title": "故事",
    "text": [
      "海滩上行走的脚印", 
      "座头鲸不惜搁浅来闻",
      "",
      "石板沿着山路爬行",
      "披的是月光打下的白霜",
      "",
      "谁家灶里跳跃的火焰",
      "是那个人清亮的眼吗",
      "",
      "从夜空的最深处",
      "有人在说着星星的话",
      "",
      "写于2015年1月14日"
    ],
    "created_at": "2015-01-14"
  }
]